{
  "version": 1,
  "strategy": {
    "primary": "notion_mcp",
    "fallback": "playwright",
    "notes": [
      "Use Notion MCP as the primary saved-view path for phase 2 execution databases.",
      "Keep direct REST as the canonical path for schema, rows, markdown content, validation, and logs.",
      "Only use Playwright if Notion MCP cannot complete the saved-view task."
    ]
  },
  "collections": [
    {
      "key": "decisions",
      "database": {
        "name": "Project Decisions",
        "databaseUrl": "https://www.notion.so/70251cb0fa1a4aed978637022131a1b1",
        "databaseId": "70251cb0fa1a4aed978637022131a1b1",
        "dataSourceId": "7bd20f7650fe4499ab7938e7d327d343",
        "destinationAlias": "project_decisions"
      },
      "views": [
        {
          "name": "Open Decisions",
          "type": "table",
          "purpose": "Show material project decisions that still need commitment.",
          "configure": "FILTER \"Status\" = \"Proposed\"; SORT BY \"Proposed On\" ASC; SHOW \"Name\", \"Status\", \"Decision Type\", \"Local Project\", \"Decision Owner\", \"Revisit By\""
        },
        {
          "name": "Decision Queue",
          "type": "board",
          "purpose": "See the decision flow grouped by status.",
          "configure": "GROUP BY \"Status\"; SHOW \"Name\", \"Decision Type\", \"Local Project\", \"Decision Owner\", \"Revisit By\""
        },
        {
          "name": "Decision History",
          "type": "table",
          "purpose": "Review committed and superseded decisions over time.",
          "configure": "SORT BY \"Decided On\" DESC; SHOW \"Name\", \"Status\", \"Decision Type\", \"Local Project\", \"Decided On\", \"Chosen Option\""
        },
        {
          "name": "Revisit Soon",
          "type": "table",
          "purpose": "Keep revisit dates visible even before formal premium reminders exist.",
          "configure": "SORT BY \"Revisit By\" ASC; SHOW \"Name\", \"Status\", \"Local Project\", \"Revisit By\", \"Expected Impact\""
        }
      ]
    },
    {
      "key": "packets",
      "database": {
        "name": "Work Packets",
        "databaseUrl": "https://www.notion.so/2ba0b69e69604a718ccacbdfcf04dd67",
        "databaseId": "2ba0b69e69604a718ccacbdfcf04dd67",
        "dataSourceId": "4ea99047102a44a5ad7afdeb71602836",
        "destinationAlias": "work_packets"
      },
      "views": [
        {
          "name": "Now",
          "type": "table",
          "purpose": "Keep the one active weekly packet front and center.",
          "configure": "FILTER \"Priority\" = \"Now\"; SORT BY \"Target Finish\" ASC; SHOW \"Name\", \"Status\", \"Priority\", \"Local Project\", \"Target Finish\", \"Goal\""
        },
        {
          "name": "Standby",
          "type": "table",
          "purpose": "Show the one fallback packet that can replace the current work quickly.",
          "configure": "FILTER \"Priority\" = \"Standby\"; SORT BY \"Target Start\" ASC; SHOW \"Name\", \"Status\", \"Priority\", \"Local Project\", \"Target Start\", \"Why Now\""
        },
        {
          "name": "Blocked",
          "type": "table",
          "purpose": "Keep blocked packets visible and easy to clear.",
          "configure": "FILTER \"Execution State\" = \"Blocked\"; SORT BY \"Target Finish\" ASC; SHOW \"Name\", \"Status\", \"Local Project\", \"Driving Decision\", \"Blocker Summary\""
        },
        {
          "name": "Done This Week",
          "type": "table",
          "purpose": "Review packets that landed recently.",
          "configure": "FILTER \"Execution State\" = \"Done\"; SORT BY \"Target Finish\" DESC; SHOW \"Name\", \"Local Project\", \"Target Finish\", \"Goal\""
        },
        {
          "name": "By Project",
          "type": "table",
          "purpose": "Review packet history in project context without embedding giant databases elsewhere.",
          "configure": "SHOW \"Name\", \"Local Project\", \"Status\", \"Priority\", \"Packet Type\", \"Target Finish\"; SORT BY \"Target Finish\" DESC"
        },
        {
          "name": "Rollover Risk",
          "type": "table",
          "purpose": "Spot packets that keep slipping so they can be narrowed or dropped.",
          "configure": "SORT BY \"Rollover Count\" DESC; SHOW \"Name\", \"Local Project\", \"Status\", \"Rollover Count\", \"Why Now\""
        }
      ]
    },
    {
      "key": "tasks",
      "database": {
        "name": "Execution Tasks",
        "databaseUrl": "https://www.notion.so/15a6a8f851504ef9b68dfd7bcf48f2ca",
        "databaseId": "15a6a8f851504ef9b68dfd7bcf48f2ca",
        "dataSourceId": "d42cd8bfc64546e7b4491ba5086e9541",
        "destinationAlias": "execution_tasks"
      },
      "views": [
        {
          "name": "My Tasks",
          "type": "table",
          "purpose": "Give the operator a simple daily execution inbox.",
          "configure": "SHOW \"Name\", \"Status\", \"Assignee\", \"Due Date\", \"Priority\", \"Work Packet\", \"Local Project\"; SORT BY \"Due Date\" ASC"
        },
        {
          "name": "Today",
          "type": "table",
          "purpose": "Keep the near-term task horizon clean and visible.",
          "configure": "SORT BY \"Due Date\" ASC; SHOW \"Name\", \"Status\", \"Due Date\", \"Priority\", \"Work Packet\""
        },
        {
          "name": "This Week",
          "type": "table",
          "purpose": "Show the weekly execution flow without turning this into a heavy sprint board.",
          "configure": "SORT BY \"Due Date\" ASC; SHOW \"Name\", \"Status\", \"Due Date\", \"Priority\", \"Task Type\", \"Work Packet\", \"Local Project\""
        },
        {
          "name": "Blocked",
          "type": "table",
          "purpose": "Keep blocked task work visible enough to clear fast.",
          "configure": "FILTER \"Execution State\" = \"Blocked\"; SORT BY \"Due Date\" ASC; SHOW \"Name\", \"Due Date\", \"Priority\", \"Work Packet\", \"Task Notes\""
        },
        {
          "name": "By Packet",
          "type": "table",
          "purpose": "Review packet-level task flow from one place.",
          "configure": "SHOW \"Name\", \"Work Packet\", \"Status\", \"Due Date\", \"Priority\", \"Local Project\"; SORT BY \"Due Date\" ASC"
        },
        {
          "name": "Ready Queue",
          "type": "table",
          "purpose": "Surface tasks that are ready to be pulled into active work.",
          "configure": "FILTER \"Execution State\" = \"Ready\"; SORT BY \"Due Date\" ASC; SHOW \"Name\", \"Due Date\", \"Priority\", \"Work Packet\", \"Local Project\""
        }
      ]
    }
  ]
}
